venv/bin/activate_this.py
venv/lib/python3.8/site-packages/_virtualenv.py
venv/lib/python3.8/site-packages/_distutils_hack/__init__.py
venv/lib/python3.8/site-packages/_distutils_hack/override.py
venv/lib/python3.8/site-packages/build/__init__.py
venv/lib/python3.8/site-packages/build/__main__.py
venv/lib/python3.8/site-packages/build/env.py
venv/lib/python3.8/site-packages/build/util.py
venv/lib/python3.8/site-packages/packaging/__about__.py
venv/lib/python3.8/site-packages/packaging/__init__.py
venv/lib/python3.8/site-packages/packaging/_elffile.py
venv/lib/python3.8/site-packages/packaging/_manylinux.py
venv/lib/python3.8/site-packages/packaging/_musllinux.py
venv/lib/python3.8/site-packages/packaging/_parser.py
venv/lib/python3.8/site-packages/packaging/_structures.py
venv/lib/python3.8/site-packages/packaging/_tokenizer.py
venv/lib/python3.8/site-packages/packaging/markers.py
venv/lib/python3.8/site-packages/packaging/requirements.py
venv/lib/python3.8/site-packages/packaging/specifiers.py
venv/lib/python3.8/site-packages/packaging/tags.py
venv/lib/python3.8/site-packages/packaging/utils.py
venv/lib/python3.8/site-packages/packaging/version.py
venv/lib/python3.8/site-packages/pep517/__init__.py
venv/lib/python3.8/site-packages/pep517/_compat.py
venv/lib/python3.8/site-packages/pep517/build.py
venv/lib/python3.8/site-packages/pep517/check.py
venv/lib/python3.8/site-packages/pep517/colorlog.py
venv/lib/python3.8/site-packages/pep517/dirtools.py
venv/lib/python3.8/site-packages/pep517/envbuild.py
venv/lib/python3.8/site-packages/pep517/meta.py
venv/lib/python3.8/site-packages/pep517/wrappers.py
venv/lib/python3.8/site-packages/pep517/in_process/__init__.py
venv/lib/python3.8/site-packages/pep517/in_process/_in_process.py
venv/lib/python3.8/site-packages/pip/__init__.py
venv/lib/python3.8/site-packages/pip/__main__.py
venv/lib/python3.8/site-packages/pip/__pip-runner__.py
venv/lib/python3.8/site-packages/pip/_internal/__init__.py
eclipse_zenoh_flow-0.0.0.dist-info/METADATA
eclipse_zenoh_flow-0.0.0.dist-info/WHEEL
eclipse_zenoh_flow-0.0.0.dist-info/licenses/LICENSE
eclipse_zenoh_flow-0.0.0.dist-info/RECORD
