Metadata-Version: 2.1
Name: eclipse-zenoh-flow
Version: 0.0.0
Summary: The python API for Eclipse Zenoh Flow
Project-URL: Bug Tracker, https://github.com/ZettaScaleLabs/zenoh-flow-python/issues
Project-URL: Source Code, https://github.com/ZettaScaleLabs/zenoh-flow-python
Project-URL: Documentation, https://readthedocs.org/projects/zenoh-flow/
License-File: LICENSE
Classifier: Development Status :: 1 - Planning
Classifier: Intended Audience :: Developers
Classifier: License :: OSI Approved :: Apache Software License
Classifier: License :: OSI Approved :: Eclipse Public License 2.0 (EPL-2.0)
Classifier: Operating System :: MacOS :: MacOS X
Classifier: Operating System :: Microsoft :: Windows
Classifier: Operating System :: POSIX :: Linux
Classifier: Programming Language :: Python :: 3 :: Only
Classifier: Programming Language :: Python :: 3.7
Classifier: Programming Language :: Python :: 3.8
Classifier: Programming Language :: Python :: 3.9
Classifier: Programming Language :: Python :: 3.10
Requires-Python: >=3.7
